expcontrol/__init__.py
expcontrol/base.py
expcontrol/event.py
expcontrol/eyelinkdep.py
expcontrol/psychopydep.py
expcontrol-0.2.3.dist-info/DESCRIPTION.rst
expcontrol-0.2.3.dist-info/METADATA
expcontrol-0.2.3.dist-info/RECORD
expcontrol-0.2.3.dist-info/WHEEL
expcontrol-0.2.3.dist-info/metadata.json
expcontrol-0.2.3.dist-info/top_level.txt
