Metadata-Version: 2.0
Name: expcontrol
Version: 0.2.3
Summary: Easy control of typical experiments in psychology and neuroscience, including stimulus presentation, timing, response collection and logging.
Home-page: http://github.com/jooh/expcontrol
Author: Johan Carlin
Author-email: johan.carlin@gmail.com
License: ISC
Keywords: psychology,neuroscience,cognitive,psychopy,vision,perception,experiment,science,research
Platform: UNKNOWN
Requires-Dist: numpy
Requires-Dist: pandas
